{"dialog_id": "20180903-103724_869_live", "turns": [{"speaker": 0, "turn": 0, "text": "Good afternoon would you like to donate to Save the Children?", "esvo": [["you", "like"]], "nsvo": [[]], "srl": {"verbs": [{"verb": "would", "description": "Good afternoon [V: would] you like to donate to Save the Children ?", "tags": ["O", "O", "B-V", "O", "O", "O", "O", "O", "O", "O", "O", "O"]}, {"verb": "like", "description": "[ARGM-DIS: Good afternoon] [ARGM-MOD: would] [ARG0: you] [V: like] [ARG1: to donate to Save the Children] ?", "tags": ["B-ARGM-DIS", "I-ARGM-DIS", "B-ARGM-MOD", "B-ARG0", "B-V", "B-ARG1", "I-ARG1", "I-ARG1", "I-ARG1", "I-ARG1", "I-ARG1", "O"]}, {"verb": "donate", "description": "Good afternoon would [ARG0: you] like to [V: donate] [ARGM-PNC: to Save the Children] ?", "tags": ["O", "O", "O", "B-ARG0", "O", "O", "B-V", "B-ARGM-PNC", "I-ARGM-PNC", "I-ARGM-PNC", "I-ARGM-PNC", "O"]}, {"verb": "Save", "description": "Good afternoon would [ARG0: you] like to donate to [V: Save] [ARG1: the Children] ?", "tags": ["O", "O", "O", "B-ARG0", "O", "O", "O", "O", "B-V", "B-ARG1", "I-ARG1", "O"]}], "words": ["Good", "afternoon", "would", "you", "like", "to", "donate", "to", "Save", "the", "Children", "?"]}, "deps": {"arc_loss": 1.0655627250671387, "tag_loss": 0.4320202171802521, "loss": 1.4975829124450684, "words": ["Good", "afternoon", "would", "you", "like", "to", "donate", "to", "Save", "the", "Children", "?"], "pos": ["ADJ", "NOUN", "AUX", "PRON", "VERB", "PART", "VERB", "PART", "VERB", "DET", "NOUN", "PUNCT"], "predicted_dependencies": ["advmod", "dep", "aux", "dep", "root", "aux", "xcomp", "prep", "advmod", "det", "dep", "dep"], "predicted_heads": [4, 1, 4, 5, 0, 7, 5, 7, 7, 11, 9, 11], "hierplane_tree": {"text": "Good afternoon would you like to donate to Save the Children ?", "root": {"word": "like", "nodeType": "root", "attributes": ["VERB"], "link": "root", "spans": [{"start": 25, "end": 30}], "children": [{"word": "you", "nodeType": "dep", "attributes": ["PRON"], "link": "dep", "spans": [{"start": 21, "end": 25}], "children": [{"word": "Good", "nodeType": "advmod", "attributes": ["ADJ"], "link": "advmod", "spans": [{"start": 0, "end": 5}], "children": [{"word": "afternoon", "nodeType": "dep", "attributes": ["NOUN"], "link": "dep", "spans": [{"start": 5, "end": 15}]}]}, {"word": "would", "nodeType": "aux", "attributes": ["AUX"], "link": "aux", "spans": [{"start": 15, "end": 21}]}]}, {"word": "donate", "nodeType": "xcomp", "attributes": ["VERB"], "link": "xcomp", "spans": [{"start": 33, "end": 40}], "children": [{"word": "to", "nodeType": "aux", "attributes": ["PART"], "link": "aux", "spans": [{"start": 30, "end": 33}]}, {"word": "to", "nodeType": "prep", "attributes": ["PART"], "link": "prep", "spans": [{"start": 40, "end": 43}]}, {"word": "Save", "nodeType": "advmod", "attributes": ["VERB"], "link": "advmod", "spans": [{"start": 43, "end": 48}], "children": [{"word": "Children", "nodeType": "dep", "attributes": ["NOUN"], "link": "dep", "spans": [{"start": 52, "end": 61}], "children": [{"word": "the", "nodeType": "det", "attributes": ["DET"], "link": "det", "spans": [{"start": 48, "end": 52}]}, {"word": "?", "nodeType": "dep", "attributes": ["PUNCT"], "link": "dep", "spans": [{"start": 61, "end": 63}]}]}]}]}]}, "nodeTypeToStyle": {"root": ["color5", "strong"], "dep": ["color5", "strong"], "nsubj": ["color1"], "nsubjpass": ["color1"], "csubj": ["color1"], "csubjpass": ["color1"], "pobj": ["color2"], "dobj": ["color2"], "iobj": ["color2"], "mark": ["color2"], "pcomp": ["color2"], "xcomp": ["color2"], "ccomp": ["color2"], "acomp": ["color2"], "aux": ["color3"], "cop": ["color3"], "det": ["color3"], "conj": ["color3"], "cc": ["color3"], "prep": ["color3"], "number": ["color3"], "possesive": ["color3"], "poss": ["color3"], "discourse": ["color3"], "expletive": ["color3"], "prt": ["color3"], "advcl": ["color3"], "mod": ["color4"], "amod": ["color4"], "tmod": ["color4"], "quantmod": ["color4"], "npadvmod": ["color4"], "infmod": ["color4"], "advmod": ["color4"], "appos": ["color4"], "nn": ["color4"], "neg": ["color0"], "punct": ["color0"]}, "linkToPosition": {"nsubj": "left", "nsubjpass": "left", "csubj": "left", "csubjpass": "left", "pobj": "right", "dobj": "right", "iobj": "right", "pcomp": "right", "xcomp": "right", "ccomp": "right", "acomp": "right"}}}}, {"speaker": 1, "turn": 0, "text": "maybe , where are the children located?", "esvo": [["the children", "located"]], "nsvo": [[]], "srl": {"verbs": [{"verb": "are", "description": "maybe , where [V: are] the children located ?", "tags": ["O", "O", "O", "B-V", "O", "O", "O", "O"]}, {"verb": "located", "description": "maybe , [ARGM-LOC: where] are [ARG1: the children] [V: located] ?", "tags": ["O", "O", "B-ARGM-LOC", "O", "B-ARG1", "I-ARG1", "B-V", "O"]}], "words": ["maybe", ",", "where", "are", "the", "children", "located", "?"]}, "deps": {"arc_loss": 0.9237959384918213, "tag_loss": 0.28655189275741577, "loss": 1.2103478908538818, "words": ["maybe", ",", "where", "are", "the", "children", "located", "?"], "pos": ["ADV", "PUNCT", "ADV", "VERB", "DET", "NOUN", "VERB", "PUNCT"], "predicted_dependencies": ["root", "advmod", "nsubj", "dep", "det", "nsubj", "dep", "punct"], "predicted_heads": [0, 1, 4, 1, 6, 4, 4, 7], "hierplane_tree": {"text": "maybe , where are the children located ?", "root": {"word": "maybe", "nodeType": "root", "attributes": ["ADV"], "link": "root", "spans": [{"start": 0, "end": 6}], "children": [{"word": ",", "nodeType": "advmod", "attributes": ["PUNCT"], "link": "advmod", "spans": [{"start": 6, "end": 8}]}, {"word": "are", "nodeType": "dep", "attributes": ["VERB"], "link": "dep", "spans": [{"start": 14, "end": 18}], "children": [{"word": "where", "nodeType": "nsubj", "attributes": ["ADV"], "link": "nsubj", "spans": [{"start": 8, "end": 14}]}, {"word": "children", "nodeType": "nsubj", "attributes": ["NOUN"], "link": "nsubj", "spans": [{"start": 22, "end": 31}], "children": [{"word": "the", "nodeType": "det", "attributes": ["DET"], "link": "det", "spans": [{"start": 18, "end": 22}]}]}, {"word": "located", "nodeType": "dep", "attributes": ["VERB"], "link": "dep", "spans": [{"start": 31, "end": 39}], "children": [{"word": "?", "nodeType": "punct", "attributes": ["PUNCT"], "link": "punct", "spans": [{"start": 39, "end": 41}]}]}]}]}, "nodeTypeToStyle": {"root": ["color5", "strong"], "dep": ["color5", "strong"], "nsubj": ["color1"], "nsubjpass": ["color1"], "csubj": ["color1"], "csubjpass": ["color1"], "pobj": ["color2"], "dobj": ["color2"], "iobj": ["color2"], "mark": ["color2"], "pcomp": ["color2"], "xcomp": ["color2"], "ccomp": ["color2"], "acomp": ["color2"], "aux": ["color3"], "cop": ["color3"], "det": ["color3"], "conj": ["color3"], "cc": ["color3"], "prep": ["color3"], "number": ["color3"], "possesive": ["color3"], "poss": ["color3"], "discourse": ["color3"], "expletive": ["color3"], "prt": ["color3"], "advcl": ["color3"], "mod": ["color4"], "amod": ["color4"], "tmod": ["color4"], "quantmod": ["color4"], "npadvmod": ["color4"], "infmod": ["color4"], "advmod": ["color4"], "appos": ["color4"], "nn": ["color4"], "neg": ["color0"], "punct": ["color0"]}, "linkToPosition": {"nsubj": "left", "nsubjpass": "left", "csubj": "left", "csubjpass": "left", "pobj": "right", "dobj": "right", "iobj": "right", "pcomp": "right", "xcomp": "right", "ccomp": "right", "acomp": "right"}}}}, {"speaker": 0, "turn": 1, "text": "The children are located in developing areas", "esvo": [["areas", "locate", "The children"], ["areas", "developing"]], "nsvo": [[]], "srl": {"verbs": [{"verb": "are", "description": "The children [V: are] located in developing areas", "tags": ["O", "O", "B-V", "O", "O", "O", "O"]}, {"verb": "located", "description": "[ARG1: The children] are [V: located] [ARGM-LOC: in developing areas]", "tags": ["B-ARG1", "I-ARG1", "O", "B-V", "B-ARGM-LOC", "I-ARGM-LOC", "I-ARGM-LOC"]}, {"verb": "developing", "description": "The children are located in [V: developing] [ARG1: areas]", "tags": ["O", "O", "O", "O", "O", "B-V", "B-ARG1"]}], "words": ["The", "children", "are", "located", "in", "developing", "areas"]}, "deps": {"arc_loss": 0.019694972783327103, "tag_loss": 0.21784856915473938, "loss": 0.23754353821277618, "words": ["The", "children", "are", "located", "in", "developing", "areas"], "pos": ["DET", "NOUN", "VERB", "VERB", "ADP", "VERB", "NOUN"], "predicted_dependencies": ["num", "nsubj", "auxpass", "root", "prep", "amod", "pobj"], "predicted_heads": [2, 4, 4, 0, 4, 7, 5], "hierplane_tree": {"text": "The children are located in developing areas", "root": {"word": "located", "nodeType": "root", "attributes": ["VERB"], "link": "root", "spans": [{"start": 17, "end": 25}], "children": [{"word": "children", "nodeType": "nsubj", "attributes": ["NOUN"], "link": "nsubj", "spans": [{"start": 4, "end": 13}], "children": [{"word": "The", "nodeType": "num", "attributes": ["DET"], "link": "num", "spans": [{"start": 0, "end": 4}]}]}, {"word": "are", "nodeType": "auxpass", "attributes": ["VERB"], "link": "auxpass", "spans": [{"start": 13, "end": 17}]}, {"word": "in", "nodeType": "prep", "attributes": ["ADP"], "link": "prep", "spans": [{"start": 25, "end": 28}], "children": [{"word": "areas", "nodeType": "pobj", "attributes": ["NOUN"], "link": "pobj", "spans": [{"start": 39, "end": 45}], "children": [{"word": "developing", "nodeType": "amod", "attributes": ["VERB"], "link": "amod", "spans": [{"start": 28, "end": 39}]}]}]}]}, "nodeTypeToStyle": {"root": ["color5", "strong"], "dep": ["color5", "strong"], "nsubj": ["color1"], "nsubjpass": ["color1"], "csubj": ["color1"], "csubjpass": ["color1"], "pobj": ["color2"], "dobj": ["color2"], "iobj": ["color2"], "mark": ["color2"], "pcomp": ["color2"], "xcomp": ["color2"], "ccomp": ["color2"], "acomp": ["color2"], "aux": ["color3"], "cop": ["color3"], "det": ["color3"], "conj": ["color3"], "cc": ["color3"], "prep": ["color3"], "number": ["color3"], "possesive": ["color3"], "poss": ["color3"], "discourse": ["color3"], "expletive": ["color3"], "prt": ["color3"], "advcl": ["color3"], "mod": ["color4"], "amod": ["color4"], "tmod": ["color4"], "quantmod": ["color4"], "npadvmod": ["color4"], "infmod": ["color4"], "advmod": ["color4"], "appos": ["color4"], "nn": ["color4"], "neg": ["color0"], "punct": ["color0"]}, "linkToPosition": {"nsubj": "left", "nsubjpass": "left", "csubj": "left", "csubjpass": "left", "pobj": "right", "dobj": "right", "iobj": "right", "pcomp": "right", "xcomp": "right", "ccomp": "right", "acomp": "right"}}}}, {"speaker": 1, "turn": 1, "text": "i can donate 2 dollars. would you ", "esvo": [["i", "donate", "2 dollars"]], "nsvo": [[], []], "srl": {"verbs": [{"verb": "can", "description": "i [V: can] donate 2 dollars . would you", "tags": ["O", "B-V", "O", "O", "O", "O", "O", "O"]}, {"verb": "donate", "description": "[ARG0: i] [ARGM-MOD: can] [V: donate] [ARG1: 2 dollars] . would you", "tags": ["B-ARG0", "B-ARGM-MOD", "B-V", "B-ARG1", "I-ARG1", "O", "O", "O"]}, {"verb": "would", "description": "i can donate 2 dollars . [V: would] you", "tags": ["O", "O", "O", "O", "O", "O", "B-V", "O"]}], "words": ["i", "can", "donate", "2", "dollars", ".", "would", "you"]}, "deps": {"arc_loss": 1.5465781688690186, "tag_loss": 0.49127647280693054, "loss": 2.0378546714782715, "words": ["i", "can", "donate", "2", "dollars", ".", "would", "you"], "pos": ["PRON", "AUX", "VERB", "NUM", "NOUN", "PUNCT", "AUX", "PRON"], "predicted_dependencies": ["nsubj", "dep", "dep", "num", "dep", "dep", "dep", "root"], "predicted_heads": [2, 8, 2, 5, 3, 8, 8, 0], "hierplane_tree": {"text": "i can donate 2 dollars . would you", "root": {"word": "you", "nodeType": "root", "attributes": ["PRON"], "link": "root", "spans": [{"start": 31, "end": 35}], "children": [{"word": "can", "nodeType": "dep", "attributes": ["AUX"], "link": "dep", "spans": [{"start": 2, "end": 6}], "children": [{"word": "i", "nodeType": "nsubj", "attributes": ["PRON"], "link": "nsubj", "spans": [{"start": 0, "end": 2}]}, {"word": "donate", "nodeType": "dep", "attributes": ["VERB"], "link": "dep", "spans": [{"start": 6, "end": 13}], "children": [{"word": "dollars", "nodeType": "dep", "attributes": ["NOUN"], "link": "dep", "spans": [{"start": 15, "end": 23}], "children": [{"word": "2", "nodeType": "num", "attributes": ["NUM"], "link": "num", "spans": [{"start": 13, "end": 15}]}]}]}]}, {"word": ".", "nodeType": "dep", "attributes": ["PUNCT"], "link": "dep", "spans": [{"start": 23, "end": 25}]}, {"word": "would", "nodeType": "dep", "attributes": ["AUX"], "link": "dep", "spans": [{"start": 25, "end": 31}]}]}, "nodeTypeToStyle": {"root": ["color5", "strong"], "dep": ["color5", "strong"], "nsubj": ["color1"], "nsubjpass": ["color1"], "csubj": ["color1"], "csubjpass": ["color1"], "pobj": ["color2"], "dobj": ["color2"], "iobj": ["color2"], "mark": ["color2"], "pcomp": ["color2"], "xcomp": ["color2"], "ccomp": ["color2"], "acomp": ["color2"], "aux": ["color3"], "cop": ["color3"], "det": ["color3"], "conj": ["color3"], "cc": ["color3"], "prep": ["color3"], "number": ["color3"], "possesive": ["color3"], "poss": ["color3"], "discourse": ["color3"], "expletive": ["color3"], "prt": ["color3"], "advcl": ["color3"], "mod": ["color4"], "amod": ["color4"], "tmod": ["color4"], "quantmod": ["color4"], "npadvmod": ["color4"], "infmod": ["color4"], "advmod": ["color4"], "appos": ["color4"], "nn": ["color4"], "neg": ["color0"], "punct": ["color0"]}, "linkToPosition": {"nsubj": "left", "nsubjpass": "left", "csubj": "left", "csubjpass": "left", "pobj": "right", "dobj": "right", "iobj": "right", "pcomp": "right", "xcomp": "right", "ccomp": "right", "acomp": "right"}}}}, {"speaker": 0, "turn": 2, "text": "That is very nice to donate the $2 from your task earnings.  Yes, I am", "esvo": [], "nsvo": [[], []], "srl": {"verbs": [{"verb": "is", "description": "[R-ARG1: That] [V: is] [ARG2: very nice] [ARG1: to donate the $ 2 from your task earnings] . Yes , I am", "tags": ["B-R-ARG1", "B-V", "B-ARG2", "I-ARG2", "B-ARG1", "I-ARG1", "I-ARG1", "I-ARG1", "I-ARG1", "I-ARG1", "I-ARG1", "I-ARG1", "I-ARG1", "O", "O", "O", "O", "O"]}, {"verb": "donate", "description": "That is very nice to [V: donate] [ARG1: the $ 2] [ARG2: from your task earnings] . Yes , I am", "tags": ["O", "O", "O", "O", "O", "B-V", "B-ARG1", "I-ARG1", "I-ARG1", "B-ARG2", "I-ARG2", "I-ARG2", "I-ARG2", "O", "O", "O", "O", "O"]}, {"verb": "am", "description": "That is very nice to donate the $ 2 from your task earnings . [ARGM-DIS: Yes] , [ARG1: I] [V: am]", "tags": ["O", "O", "O", "O", "O", "O", "O", "O", "O", "O", "O", "O", "O", "O", "B-ARGM-DIS", "O", "B-ARG1", "B-V"]}], "words": ["That", "is", "very", "nice", "to", "donate", "the", "$", "2", "from", "your", "task", "earnings", ".", "Yes", ",", "I", "am"]}, "deps": {"arc_loss": 0.3698011338710785, "tag_loss": 0.3156660795211792, "loss": 0.6854672431945801, "words": ["That", "is", "very", "nice", "to", "donate", "the", "$", "2", "from", "your", "task", "earnings", ".", "Yes", ",", "I", "am"], "pos": ["DET", "VERB", "ADV", "ADJ", "PART", "VERB", "DET", "SYM", "NUM", "ADP", "PRON", "NOUN", "NOUN", "PUNCT", "INTJ", "PUNCT", "PRON", "VERB"], "predicted_dependencies": ["nsubj", "cop", "advmod", "root", "mark", "ccomp", "det", "dep", "number", "prep", "pobj", "amod", "dep", "mark", "dep", "dep", "dep", "dep"], "predicted_heads": [4, 4, 4, 0, 6, 4, 8, 6, 8, 6, 10, 13, 10, 15, 13, 15, 15, 15], "hierplane_tree": {"text": "That is very nice to donate the $ 2 from your task earnings . Yes , I am", "root": {"word": "nice", "nodeType": "root", "attributes": ["ADJ"], "link": "root", "spans": [{"start": 13, "end": 18}], "children": [{"word": "That", "nodeType": "nsubj", "attributes": ["DET"], "link": "nsubj", "spans": [{"start": 0, "end": 5}]}, {"word": "is", "nodeType": "cop", "attributes": ["VERB"], "link": "cop", "spans": [{"start": 5, "end": 8}]}, {"word": "very", "nodeType": "advmod", "attributes": ["ADV"], "link": "advmod", "spans": [{"start": 8, "end": 13}]}, {"word": "donate", "nodeType": "ccomp", "attributes": ["VERB"], "link": "ccomp", "spans": [{"start": 21, "end": 28}], "children": [{"word": "to", "nodeType": "mark", "attributes": ["PART"], "link": "mark", "spans": [{"start": 18, "end": 21}]}, {"word": "$", "nodeType": "dep", "attributes": ["SYM"], "link": "dep", "spans": [{"start": 32, "end": 34}], "children": [{"word": "the", "nodeType": "det", "attributes": ["DET"], "link": "det", "spans": [{"start": 28, "end": 32}]}, {"word": "2", "nodeType": "number", "attributes": ["NUM"], "link": "number", "spans": [{"start": 34, "end": 36}]}]}, {"word": "from", "nodeType": "prep", "attributes": ["ADP"], "link": "prep", "spans": [{"start": 36, "end": 41}], "children": [{"word": "your", "nodeType": "pobj", "attributes": ["PRON"], "link": "pobj", "spans": [{"start": 41, "end": 46}]}, {"word": "earnings", "nodeType": "dep", "attributes": ["NOUN"], "link": "dep", "spans": [{"start": 51, "end": 60}], "children": [{"word": "task", "nodeType": "amod", "attributes": ["NOUN"], "link": "amod", "spans": [{"start": 46, "end": 51}]}, {"word": "Yes", "nodeType": "dep", "attributes": ["INTJ"], "link": "dep", "spans": [{"start": 62, "end": 66}], "children": [{"word": ".", "nodeType": "mark", "attributes": ["PUNCT"], "link": "mark", "spans": [{"start": 60, "end": 62}]}, {"word": ",", "nodeType": "dep", "attributes": ["PUNCT"], "link": "dep", "spans": [{"start": 66, "end": 68}]}, {"word": "I", "nodeType": "dep", "attributes": ["PRON"], "link": "dep", "spans": [{"start": 68, "end": 70}]}, {"word": "am", "nodeType": "dep", "attributes": ["VERB"], "link": "dep", "spans": [{"start": 70, "end": 73}]}]}]}]}]}]}, "nodeTypeToStyle": {"root": ["color5", "strong"], "dep": ["color5", "strong"], "nsubj": ["color1"], "nsubjpass": ["color1"], "csubj": ["color1"], "csubjpass": ["color1"], "pobj": ["color2"], "dobj": ["color2"], "iobj": ["color2"], "mark": ["color2"], "pcomp": ["color2"], "xcomp": ["color2"], "ccomp": ["color2"], "acomp": ["color2"], "aux": ["color3"], "cop": ["color3"], "det": ["color3"], "conj": ["color3"], "cc": ["color3"], "prep": ["color3"], "number": ["color3"], "possesive": ["color3"], "poss": ["color3"], "discourse": ["color3"], "expletive": ["color3"], "prt": ["color3"], "advcl": ["color3"], "mod": ["color4"], "amod": ["color4"], "tmod": ["color4"], "quantmod": ["color4"], "npadvmod": ["color4"], "infmod": ["color4"], "advmod": ["color4"], "appos": ["color4"], "nn": ["color4"], "neg": ["color0"], "punct": ["color0"]}, "linkToPosition": {"nsubj": "left", "nsubjpass": "left", "csubj": "left", "csubjpass": "left", "pobj": "right", "dobj": "right", "iobj": "right", "pcomp": "right", "xcomp": "right", "ccomp": "right", "acomp": "right"}}}}, {"speaker": 1, "turn": 2, "text": "where should i send the money? will you just take cash?", "esvo": [["i", "send", "the money"], ["you", "take", "cash"]], "nsvo": [[{"subject": ["i"], "predicate": ["send"], "object": ["money"]}], [{"subject": ["you"], "predicate": ["take"], "object": ["cash"]}]], "srl": {"verbs": [{"verb": "should", "description": "where [V: should] i send the money ? will you just take cash ?", "tags": ["O", "B-V", "O", "O", "O", "O", "O", "O", "O", "O", "O", "O", "O"]}, {"verb": "send", "description": "[ARG2: where] [ARGM-MOD: should] [ARG0: i] [V: send] [ARG1: the money] ? will you just take cash ?", "tags": ["B-ARG2", "B-ARGM-MOD", "B-ARG0", "B-V", "B-ARG1", "I-ARG1", "O", "O", "O", "O", "O", "O", "O"]}, {"verb": "will", "description": "where should i send the money ? [V: will] you just take cash ?", "tags": ["O", "O", "O", "O", "O", "O", "O", "B-V", "O", "O", "O", "O", "O"]}, {"verb": "take", "description": "where should i send the money ? [ARGM-MOD: will] [ARG0: you] [ARGM-ADV: just] [V: take] [ARG1: cash] ?", "tags": ["O", "O", "O", "O", "O", "O", "O", "B-ARGM-MOD", "B-ARG0", "B-ARGM-ADV", "B-V", "B-ARG1", "O"]}], "words": ["where", "should", "i", "send", "the", "money", "?", "will", "you", "just", "take", "cash", "?"]}, "deps": {"arc_loss": 1.8008227348327637, "tag_loss": 0.45022836327552795, "loss": 2.251051187515259, "words": ["where", "should", "i", "send", "the", "money", "?", "will", "you", "just", "take", "cash", "?"], "pos": ["ADV", "AUX", "PRON", "VERB", "DET", "NOUN", "PUNCT", "AUX", "PRON", "ADV", "VERB", "NOUN", "PUNCT"], "predicted_dependencies": ["advmod", "aux", "root", "dep", "dep", "dep", "dep", "aux", "nsubj", "advmod", "dep", "dobj", "punct"], "predicted_heads": [4, 4, 0, 3, 6, 4, 4, 11, 11, 11, 7, 11, 11], "hierplane_tree": {"text": "where should i send the money ? will you just take cash ?", "root": {"word": "i", "nodeType": "root", "attributes": ["PRON"], "link": "root", "spans": [{"start": 13, "end": 15}], "children": [{"word": "send", "nodeType": "dep", "attributes": ["VERB"], "link": "dep", "spans": [{"start": 15, "end": 20}], "children": [{"word": "where", "nodeType": "advmod", "attributes": ["ADV"], "link": "advmod", "spans": [{"start": 0, "end": 6}]}, {"word": "should", "nodeType": "aux", "attributes": ["AUX"], "link": "aux", "spans": [{"start": 6, "end": 13}]}, {"word": "money", "nodeType": "dep", "attributes": ["NOUN"], "link": "dep", "spans": [{"start": 24, "end": 30}], "children": [{"word": "the", "nodeType": "dep", "attributes": ["DET"], "link": "dep", "spans": [{"start": 20, "end": 24}]}]}, {"word": "?", "nodeType": "dep", "attributes": ["PUNCT"], "link": "dep", "spans": [{"start": 30, "end": 32}], "children": [{"word": "take", "nodeType": "dep", "attributes": ["VERB"], "link": "dep", "spans": [{"start": 46, "end": 51}], "children": [{"word": "will", "nodeType": "aux", "attributes": ["AUX"], "link": "aux", "spans": [{"start": 32, "end": 37}]}, {"word": "you", "nodeType": "nsubj", "attributes": ["PRON"], "link": "nsubj", "spans": [{"start": 37, "end": 41}]}, {"word": "just", "nodeType": "advmod", "attributes": ["ADV"], "link": "advmod", "spans": [{"start": 41, "end": 46}]}, {"word": "cash", "nodeType": "dobj", "attributes": ["NOUN"], "link": "dobj", "spans": [{"start": 51, "end": 56}]}, {"word": "?", "nodeType": "punct", "attributes": ["PUNCT"], "link": "punct", "spans": [{"start": 56, "end": 58}]}]}]}]}]}, "nodeTypeToStyle": {"root": ["color5", "strong"], "dep": ["color5", "strong"], "nsubj": ["color1"], "nsubjpass": ["color1"], "csubj": ["color1"], "csubjpass": ["color1"], "pobj": ["color2"], "dobj": ["color2"], "iobj": ["color2"], "mark": ["color2"], "pcomp": ["color2"], "xcomp": ["color2"], "ccomp": ["color2"], "acomp": ["color2"], "aux": ["color3"], "cop": ["color3"], "det": ["color3"], "conj": ["color3"], "cc": ["color3"], "prep": ["color3"], "number": ["color3"], "possesive": ["color3"], "poss": ["color3"], "discourse": ["color3"], "expletive": ["color3"], "prt": ["color3"], "advcl": ["color3"], "mod": ["color4"], "amod": ["color4"], "tmod": ["color4"], "quantmod": ["color4"], "npadvmod": ["color4"], "infmod": ["color4"], "advmod": ["color4"], "appos": ["color4"], "nn": ["color4"], "neg": ["color0"], "punct": ["color0"]}, "linkToPosition": {"nsubj": "left", "nsubjpass": "left", "csubj": "left", "csubjpass": "left", "pobj": "right", "dobj": "right", "iobj": "right", "pcomp": "right", "xcomp": "right", "ccomp": "right", "acomp": "right"}}}}, {"speaker": 0, "turn": 3, "text": "The money is just taken from your task bonus payment", "esvo": [["your bonus payment", "take", "The money"]], "nsvo": [[]], "srl": {"verbs": [{"verb": "is", "description": "The money [V: is] just taken from your task bonus payment", "tags": ["O", "O", "B-V", "O", "O", "O", "O", "O", "O", "O"]}, {"verb": "taken", "description": "[ARG1: The money] is [ARGM-ADV: just] [V: taken] [ARG2: from your task bonus payment]", "tags": ["B-ARG1", "I-ARG1", "O", "B-ARGM-ADV", "B-V", "B-ARG2", "I-ARG2", "I-ARG2", "I-ARG2", "I-ARG2"]}], "words": ["The", "money", "is", "just", "taken", "from", "your", "task", "bonus", "payment"]}, "deps": {"arc_loss": 0.046484969556331635, "tag_loss": 0.33378154039382935, "loss": 0.3802665174007416, "words": ["The", "money", "is", "just", "taken", "from", "your", "task", "bonus", "payment"], "pos": ["DET", "NOUN", "VERB", "ADV", "VERB", "ADP", "PRON", "NOUN", "NOUN", "NOUN"], "predicted_dependencies": ["dep", "nsubj", "auxpass", "advmod", "root", "prep", "dep", "amod", "nn", "pobj"], "predicted_heads": [2, 5, 5, 5, 0, 5, 10, 10, 10, 6], "hierplane_tree": {"text": "The money is just taken from your task bonus payment", "root": {"word": "taken", "nodeType": "root", "attributes": ["VERB"], "link": "root", "spans": [{"start": 18, "end": 24}], "children": [{"word": "money", "nodeType": "nsubj", "attributes": ["NOUN"], "link": "nsubj", "spans": [{"start": 4, "end": 10}], "children": [{"word": "The", "nodeType": "dep", "attributes": ["DET"], "link": "dep", "spans": [{"start": 0, "end": 4}]}]}, {"word": "is", "nodeType": "auxpass", "attributes": ["VERB"], "link": "auxpass", "spans": [{"start": 10, "end": 13}]}, {"word": "just", "nodeType": "advmod", "attributes": ["ADV"], "link": "advmod", "spans": [{"start": 13, "end": 18}]}, {"word": "from", "nodeType": "prep", "attributes": ["ADP"], "link": "prep", "spans": [{"start": 24, "end": 29}], "children": [{"word": "payment", "nodeType": "pobj", "attributes": ["NOUN"], "link": "pobj", "spans": [{"start": 45, "end": 53}], "children": [{"word": "your", "nodeType": "dep", "attributes": ["PRON"], "link": "dep", "spans": [{"start": 29, "end": 34}]}, {"word": "task", "nodeType": "amod", "attributes": ["NOUN"], "link": "amod", "spans": [{"start": 34, "end": 39}]}, {"word": "bonus", "nodeType": "nn", "attributes": ["NOUN"], "link": "nn", "spans": [{"start": 39, "end": 45}]}]}]}]}, "nodeTypeToStyle": {"root": ["color5", "strong"], "dep": ["color5", "strong"], "nsubj": ["color1"], "nsubjpass": ["color1"], "csubj": ["color1"], "csubjpass": ["color1"], "pobj": ["color2"], "dobj": ["color2"], "iobj": ["color2"], "mark": ["color2"], "pcomp": ["color2"], "xcomp": ["color2"], "ccomp": ["color2"], "acomp": ["color2"], "aux": ["color3"], "cop": ["color3"], "det": ["color3"], "conj": ["color3"], "cc": ["color3"], "prep": ["color3"], "number": ["color3"], "possesive": ["color3"], "poss": ["color3"], "discourse": ["color3"], "expletive": ["color3"], "prt": ["color3"], "advcl": ["color3"], "mod": ["color4"], "amod": ["color4"], "tmod": ["color4"], "quantmod": ["color4"], "npadvmod": ["color4"], "infmod": ["color4"], "advmod": ["color4"], "appos": ["color4"], "nn": ["color4"], "neg": ["color0"], "punct": ["color0"]}, "linkToPosition": {"nsubj": "left", "nsubjpass": "left", "csubj": "left", "csubjpass": "left", "pobj": "right", "dobj": "right", "iobj": "right", "pcomp": "right", "xcomp": "right", "ccomp": "right", "acomp": "right"}}}}, {"speaker": 1, "turn": 3, "text": "i know, i was just role playing. lol. this gets a bit silly now", "esvo": [["i", "know"]], "nsvo": [[{"subject": ["i"], "predicate": ["playing"], "object": ["role"]}], [], []], "srl": {"verbs": [{"verb": "know", "description": "[ARG0: i] [V: know] , [ARG1: i was just role playing] . lol . this gets a bit silly now", "tags": ["B-ARG0", "B-V", "O", "B-ARG1", "I-ARG1", "I-ARG1", "I-ARG1", "I-ARG1", "O", "O", "O", "O", "O", "O", "O", "O", "O"]}, {"verb": "was", "description": "i know , [ARG1: i] [V: was] just [ARG2: role playing] . lol . this gets a bit silly now", "tags": ["O", "O", "O", "B-ARG1", "B-V", "O", "B-ARG2", "I-ARG2", "O", "O", "O", "O", "O", "O", "O", "O", "O"]}, {"verb": "gets", "description": "i know , i was just role playing . lol . [ARG1: this] [V: gets] [ARG2: a bit silly] [ARGM-TMP: now]", "tags": ["O", "O", "O", "O", "O", "O", "O", "O", "O", "O", "O", "B-ARG1", "B-V", "B-ARG2", "I-ARG2", "I-ARG2", "B-ARGM-TMP"]}], "words": ["i", "know", ",", "i", "was", "just", "role", "playing", ".", "lol", ".", "this", "gets", "a", "bit", "silly", "now"]}, "deps": {"arc_loss": 0.7686437368392944, "tag_loss": 0.48753172159194946, "loss": 1.2561755180358887, "words": ["i", "know", ",", "i", "was", "just", "role", "playing", ".", "lol", ".", "this", "gets", "a", "bit", "silly", "now"], "pos": ["PRON", "VERB", "PUNCT", "PRON", "VERB", "ADV", "NOUN", "NOUN", "PUNCT", "INTJ", "PUNCT", "DET", "VERB", "DET", "NOUN", "ADJ", "ADV"], "predicted_dependencies": ["discourse", "root", "punct", "nsubj", "dep", "advmod", "dep", "dep", "punct", "dep", "dep", "nsubj", "dep", "dep", "dep", "dep", "dep"], "predicted_heads": [2, 0, 2, 5, 2, 5, 5, 7, 10, 8, 13, 13, 7, 15, 16, 13, 16], "hierplane_tree": {"text": "i know , i was just role playing . lol . this gets a bit silly now", "root": {"word": "know", "nodeType": "root", "attributes": ["VERB"], "link": "root", "spans": [{"start": 2, "end": 7}], "children": [{"word": "i", "nodeType": "discourse", "attributes": ["PRON"], "link": "discourse", "spans": [{"start": 0, "end": 2}]}, {"word": ",", "nodeType": "punct", "attributes": ["PUNCT"], "link": "punct", "spans": [{"start": 7, "end": 9}]}, {"word": "was", "nodeType": "dep", "attributes": ["VERB"], "link": "dep", "spans": [{"start": 11, "end": 15}], "children": [{"word": "i", "nodeType": "nsubj", "attributes": ["PRON"], "link": "nsubj", "spans": [{"start": 9, "end": 11}]}, {"word": "just", "nodeType": "advmod", "attributes": ["ADV"], "link": "advmod", "spans": [{"start": 15, "end": 20}]}, {"word": "role", "nodeType": "dep", "attributes": ["NOUN"], "link": "dep", "spans": [{"start": 20, "end": 25}], "children": [{"word": "playing", "nodeType": "dep", "attributes": ["NOUN"], "link": "dep", "spans": [{"start": 25, "end": 33}], "children": [{"word": "lol", "nodeType": "dep", "attributes": ["INTJ"], "link": "dep", "spans": [{"start": 35, "end": 39}], "children": [{"word": ".", "nodeType": "punct", "attributes": ["PUNCT"], "link": "punct", "spans": [{"start": 33, "end": 35}]}]}]}, {"word": "gets", "nodeType": "dep", "attributes": ["VERB"], "link": "dep", "spans": [{"start": 46, "end": 51}], "children": [{"word": ".", "nodeType": "dep", "attributes": ["PUNCT"], "link": "dep", "spans": [{"start": 39, "end": 41}]}, {"word": "this", "nodeType": "nsubj", "attributes": ["DET"], "link": "nsubj", "spans": [{"start": 41, "end": 46}]}, {"word": "silly", "nodeType": "dep", "attributes": ["ADJ"], "link": "dep", "spans": [{"start": 57, "end": 63}], "children": [{"word": "bit", "nodeType": "dep", "attributes": ["NOUN"], "link": "dep", "spans": [{"start": 53, "end": 57}], "children": [{"word": "a", "nodeType": "dep", "attributes": ["DET"], "link": "dep", "spans": [{"start": 51, "end": 53}]}]}, {"word": "now", "nodeType": "dep", "attributes": ["ADV"], "link": "dep", "spans": [{"start": 63, "end": 67}]}]}]}]}]}]}, "nodeTypeToStyle": {"root": ["color5", "strong"], "dep": ["color5", "strong"], "nsubj": ["color1"], "nsubjpass": ["color1"], "csubj": ["color1"], "csubjpass": ["color1"], "pobj": ["color2"], "dobj": ["color2"], "iobj": ["color2"], "mark": ["color2"], "pcomp": ["color2"], "xcomp": ["color2"], "ccomp": ["color2"], "acomp": ["color2"], "aux": ["color3"], "cop": ["color3"], "det": ["color3"], "conj": ["color3"], "cc": ["color3"], "prep": ["color3"], "number": ["color3"], "possesive": ["color3"], "poss": ["color3"], "discourse": ["color3"], "expletive": ["color3"], "prt": ["color3"], "advcl": ["color3"], "mod": ["color4"], "amod": ["color4"], "tmod": ["color4"], "quantmod": ["color4"], "npadvmod": ["color4"], "infmod": ["color4"], "advmod": ["color4"], "appos": ["color4"], "nn": ["color4"], "neg": ["color0"], "punct": ["color0"]}, "linkToPosition": {"nsubj": "left", "nsubjpass": "left", "csubj": "left", "csubjpass": "left", "pobj": "right", "dobj": "right", "iobj": "right", "pcomp": "right", "xcomp": "right", "ccomp": "right", "acomp": "right"}}}}, {"speaker": 0, "turn": 4, "text": "It does!  ", "esvo": [["It", "does", " "]], "nsvo": [[]], "srl": {"verbs": [{"verb": "does", "description": "It [V: does] !", "tags": ["O", "B-V", "O"]}], "words": ["It", "does", "!"]}, "deps": {"arc_loss": 0.07685839384794235, "tag_loss": 0.059479426592588425, "loss": 0.13633781671524048, "words": ["It", "does", "!"], "pos": ["PRON", "VERB", "PUNCT"], "predicted_dependencies": ["nsubj", "root", "dep"], "predicted_heads": [2, 0, 2], "hierplane_tree": {"text": "It does !", "root": {"word": "does", "nodeType": "root", "attributes": ["VERB"], "link": "root", "spans": [{"start": 3, "end": 8}], "children": [{"word": "It", "nodeType": "nsubj", "attributes": ["PRON"], "link": "nsubj", "spans": [{"start": 0, "end": 3}]}, {"word": "!", "nodeType": "dep", "attributes": ["PUNCT"], "link": "dep", "spans": [{"start": 8, "end": 10}]}]}, "nodeTypeToStyle": {"root": ["color5", "strong"], "dep": ["color5", "strong"], "nsubj": ["color1"], "nsubjpass": ["color1"], "csubj": ["color1"], "csubjpass": ["color1"], "pobj": ["color2"], "dobj": ["color2"], "iobj": ["color2"], "mark": ["color2"], "pcomp": ["color2"], "xcomp": ["color2"], "ccomp": ["color2"], "acomp": ["color2"], "aux": ["color3"], "cop": ["color3"], "det": ["color3"], "conj": ["color3"], "cc": ["color3"], "prep": ["color3"], "number": ["color3"], "possesive": ["color3"], "poss": ["color3"], "discourse": ["color3"], "expletive": ["color3"], "prt": ["color3"], "advcl": ["color3"], "mod": ["color4"], "amod": ["color4"], "tmod": ["color4"], "quantmod": ["color4"], "npadvmod": ["color4"], "infmod": ["color4"], "advmod": ["color4"], "appos": ["color4"], "nn": ["color4"], "neg": ["color0"], "punct": ["color0"]}, "linkToPosition": {"nsubj": "left", "nsubjpass": "left", "csubj": "left", "csubjpass": "left", "pobj": "right", "dobj": "right", "iobj": "right", "pcomp": "right", "xcomp": "right", "ccomp": "right", "acomp": "right"}}}}, {"speaker": 1, "turn": 4, "text": "my second line was asking about my tax records but it cut me off and sent early. lol", "esvo": [["my second line", "asking"], ["it", "cut", "me"]], "nsvo": [[], []], "srl": {"verbs": [{"verb": "was", "description": "[ARG1: my second line] [V: was] [ARG2: asking about my tax records] but it cut me off and sent early . lol", "tags": ["B-ARG1", "I-ARG1", "I-ARG1", "B-V", "B-ARG2", "I-ARG2", "I-ARG2", "I-ARG2", "I-ARG2", "O", "O", "O", "O", "O", "O", "O", "O", "O", "O"]}, {"verb": "asking", "description": "[ARG0: my second line] was [V: asking] [ARG1: about my tax records] but it cut me off and sent early . lol", "tags": ["B-ARG0", "I-ARG0", "I-ARG0", "O", "B-V", "B-ARG1", "I-ARG1", "I-ARG1", "I-ARG1", "O", "O", "O", "O", "O", "O", "O", "O", "O", "O"]}, {"verb": "cut", "description": "my second line was asking about my tax records but [ARG0: it] [V: cut] [ARG1: me] off and sent early . lol", "tags": ["O", "O", "O", "O", "O", "O", "O", "O", "O", "O", "B-ARG0", "B-V", "B-ARG1", "O", "O", "O", "O", "O", "O"]}, {"verb": "sent", "description": "my second line was asking about my tax records but [ARG0: it] cut me off and [V: sent] [ARGM-TMP: early] . [ARGM-DIS: lol]", "tags": ["O", "O", "O", "O", "O", "O", "O", "O", "O", "O", "B-ARG0", "O", "O", "O", "O", "B-V", "B-ARGM-TMP", "O", "B-ARGM-DIS"]}], "words": ["my", "second", "line", "was", "asking", "about", "my", "tax", "records", "but", "it", "cut", "me", "off", "and", "sent", "early", ".", "lol"]}, "deps": {"arc_loss": 0.47504159808158875, "tag_loss": 0.5043681263923645, "loss": 0.9794096946716309, "words": ["my", "second", "line", "was", "asking", "about", "my", "tax", "records", "but", "it", "cut", "me", "off", "and", "sent", "early", ".", "lol"], "pos": ["PRON", "ADJ", "NOUN", "VERB", "VERB", "ADP", "PRON", "NOUN", "NOUN", "CCONJ", "PRON", "VERB", "PRON", "ADP", "CCONJ", "VERB", "ADV", "PUNCT", "NOUN"], "predicted_dependencies": ["amod", "nn", "nsubj", "cop", "root", "prep", "dep", "nn", "dobj", "dep", "nsubj", "dep", "dep", "dep", "dep", "dep", "dep", "dep", "dep"], "predicted_heads": [3, 3, 5, 5, 0, 5, 9, 9, 5, 5, 12, 5, 12, 13, 14, 12, 16, 19, 17], "hierplane_tree": {"text": "my second line was asking about my tax records but it cut me off and sent early . lol", "root": {"word": "asking", "nodeType": "root", "attributes": ["VERB"], "link": "root", "spans": [{"start": 19, "end": 26}], "children": [{"word": "line", "nodeType": "nsubj", "attributes": ["NOUN"], "link": "nsubj", "spans": [{"start": 10, "end": 15}], "children": [{"word": "my", "nodeType": "amod", "attributes": ["PRON"], "link": "amod", "spans": [{"start": 0, "end": 3}]}, {"word": "second", "nodeType": "nn", "attributes": ["ADJ"], "link": "nn", "spans": [{"start": 3, "end": 10}]}]}, {"word": "was", "nodeType": "cop", "attributes": ["VERB"], "link": "cop", "spans": [{"start": 15, "end": 19}]}, {"word": "about", "nodeType": "prep", "attributes": ["ADP"], "link": "prep", "spans": [{"start": 26, "end": 32}]}, {"word": "records", "nodeType": "dobj", "attributes": ["NOUN"], "link": "dobj", "spans": [{"start": 39, "end": 47}], "children": [{"word": "my", "nodeType": "dep", "attributes": ["PRON"], "link": "dep", "spans": [{"start": 32, "end": 35}]}, {"word": "tax", "nodeType": "nn", "attributes": ["NOUN"], "link": "nn", "spans": [{"start": 35, "end": 39}]}]}, {"word": "but", "nodeType": "dep", "attributes": ["CCONJ"], "link": "dep", "spans": [{"start": 47, "end": 51}]}, {"word": "cut", "nodeType": "dep", "attributes": ["VERB"], "link": "dep", "spans": [{"start": 54, "end": 58}], "children": [{"word": "it", "nodeType": "nsubj", "attributes": ["PRON"], "link": "nsubj", "spans": [{"start": 51, "end": 54}]}, {"word": "me", "nodeType": "dep", "attributes": ["PRON"], "link": "dep", "spans": [{"start": 58, "end": 61}], "children": [{"word": "off", "nodeType": "dep", "attributes": ["ADP"], "link": "dep", "spans": [{"start": 61, "end": 65}], "children": [{"word": "and", "nodeType": "dep", "attributes": ["CCONJ"], "link": "dep", "spans": [{"start": 65, "end": 69}]}]}]}, {"word": "sent", "nodeType": "dep", "attributes": ["VERB"], "link": "dep", "spans": [{"start": 69, "end": 74}], "children": [{"word": "early", "nodeType": "dep", "attributes": ["ADV"], "link": "dep", "spans": [{"start": 74, "end": 80}], "children": [{"word": "lol", "nodeType": "dep", "attributes": ["NOUN"], "link": "dep", "spans": [{"start": 82, "end": 86}], "children": [{"word": ".", "nodeType": "dep", "attributes": ["PUNCT"], "link": "dep", "spans": [{"start": 80, "end": 82}]}]}]}]}]}]}, "nodeTypeToStyle": {"root": ["color5", "strong"], "dep": ["color5", "strong"], "nsubj": ["color1"], "nsubjpass": ["color1"], "csubj": ["color1"], "csubjpass": ["color1"], "pobj": ["color2"], "dobj": ["color2"], "iobj": ["color2"], "mark": ["color2"], "pcomp": ["color2"], "xcomp": ["color2"], "ccomp": ["color2"], "acomp": ["color2"], "aux": ["color3"], "cop": ["color3"], "det": ["color3"], "conj": ["color3"], "cc": ["color3"], "prep": ["color3"], "number": ["color3"], "possesive": ["color3"], "poss": ["color3"], "discourse": ["color3"], "expletive": ["color3"], "prt": ["color3"], "advcl": ["color3"], "mod": ["color4"], "amod": ["color4"], "tmod": ["color4"], "quantmod": ["color4"], "npadvmod": ["color4"], "infmod": ["color4"], "advmod": ["color4"], "appos": ["color4"], "nn": ["color4"], "neg": ["color0"], "punct": ["color0"]}, "linkToPosition": {"nsubj": "left", "nsubjpass": "left", "csubj": "left", "csubjpass": "left", "pobj": "right", "dobj": "right", "iobj": "right", "pcomp": "right", "xcomp": "right", "ccomp": "right", "acomp": "right"}}}}, {"speaker": 0, "turn": 5, "text": "Lol!  10 chat turns seems like forever!", "esvo": [["Lol   chat turns", "seems", "like"]], "nsvo": [[], []], "srl": {"verbs": [{"verb": "seems", "description": "[ARGM-DIS: Lol] ! [ARG1: 10 chat turns] [V: seems] [C-ARG1: like forever] !", "tags": ["B-ARGM-DIS", "O", "B-ARG1", "I-ARG1", "I-ARG1", "B-V", "B-C-ARG1", "I-C-ARG1", "O"]}], "words": ["Lol", "!", "10", "chat", "turns", "seems", "like", "forever", "!"]}, "deps": {"arc_loss": 0.43579497933387756, "tag_loss": 0.25864988565444946, "loss": 0.6944448947906494, "words": ["Lol", "!", "10", "chat", "turns", "seems", "like", "forever", "!"], "pos": ["INTJ", "PUNCT", "NUM", "NOUN", "NOUN", "VERB", "ADP", "ADV", "PUNCT"], "predicted_dependencies": ["root", "dep", "dep", "amod", "dep", "dep", "prep", "dep", "dep"], "predicted_heads": [0, 1, 2, 5, 1, 1, 6, 7, 7], "hierplane_tree": {"text": "Lol ! 10 chat turns seems like forever !", "root": {"word": "Lol", "nodeType": "root", "attributes": ["INTJ"], "link": "root", "spans": [{"start": 0, "end": 4}], "children": [{"word": "!", "nodeType": "dep", "attributes": ["PUNCT"], "link": "dep", "spans": [{"start": 4, "end": 6}], "children": [{"word": "10", "nodeType": "dep", "attributes": ["NUM"], "link": "dep", "spans": [{"start": 6, "end": 9}]}]}, {"word": "turns", "nodeType": "dep", "attributes": ["NOUN"], "link": "dep", "spans": [{"start": 14, "end": 20}], "children": [{"word": "chat", "nodeType": "amod", "attributes": ["NOUN"], "link": "amod", "spans": [{"start": 9, "end": 14}]}]}, {"word": "seems", "nodeType": "dep", "attributes": ["VERB"], "link": "dep", "spans": [{"start": 20, "end": 26}], "children": [{"word": "like", "nodeType": "prep", "attributes": ["ADP"], "link": "prep", "spans": [{"start": 26, "end": 31}], "children": [{"word": "forever", "nodeType": "dep", "attributes": ["ADV"], "link": "dep", "spans": [{"start": 31, "end": 39}]}, {"word": "!", "nodeType": "dep", "attributes": ["PUNCT"], "link": "dep", "spans": [{"start": 39, "end": 41}]}]}]}]}, "nodeTypeToStyle": {"root": ["color5", "strong"], "dep": ["color5", "strong"], "nsubj": ["color1"], "nsubjpass": ["color1"], "csubj": ["color1"], "csubjpass": ["color1"], "pobj": ["color2"], "dobj": ["color2"], "iobj": ["color2"], "mark": ["color2"], "pcomp": ["color2"], "xcomp": ["color2"], "ccomp": ["color2"], "acomp": ["color2"], "aux": ["color3"], "cop": ["color3"], "det": ["color3"], "conj": ["color3"], "cc": ["color3"], "prep": ["color3"], "number": ["color3"], "possesive": ["color3"], "poss": ["color3"], "discourse": ["color3"], "expletive": ["color3"], "prt": ["color3"], "advcl": ["color3"], "mod": ["color4"], "amod": ["color4"], "tmod": ["color4"], "quantmod": ["color4"], "npadvmod": ["color4"], "infmod": ["color4"], "advmod": ["color4"], "appos": ["color4"], "nn": ["color4"], "neg": ["color0"], "punct": ["color0"]}, "linkToPosition": {"nsubj": "left", "nsubjpass": "left", "csubj": "left", "csubjpass": "left", "pobj": "right", "dobj": "right", "iobj": "right", "pcomp": "right", "xcomp": "right", "ccomp": "right", "acomp": "right"}}}}, {"speaker": 1, "turn": 5, "text": "where are you at? i am in the usa", "esvo": [["i", "am"]], "nsvo": [[], [{"subject": ["i"], "predicate": ["am"], "object": ["usa"]}]], "srl": {"verbs": [{"verb": "are", "description": "where [V: are] [ARG1: you] [ARG2: at] ? i am in the usa", "tags": ["O", "B-V", "B-ARG1", "B-ARG2", "O", "O", "O", "O", "O", "O"]}, {"verb": "am", "description": "where are you at ? [ARG1: i] [V: am] [ARG2: in the usa]", "tags": ["O", "O", "O", "O", "O", "B-ARG1", "B-V", "B-ARG2", "I-ARG2", "I-ARG2"]}], "words": ["where", "are", "you", "at", "?", "i", "am", "in", "the", "usa"]}, "deps": {"arc_loss": 0.4636722505092621, "tag_loss": 0.18998833000659943, "loss": 0.6536605954170227, "words": ["where", "are", "you", "at", "?", "i", "am", "in", "the", "usa"], "pos": ["ADV", "VERB", "PRON", "ADP", "PUNCT", "PRON", "VERB", "ADP", "DET", "NOUN"], "predicted_dependencies": ["nsubj", "root", "nsubj", "advmod", "prep", "dep", "dep", "prep", "det", "pobj"], "predicted_heads": [2, 0, 2, 2, 3, 7, 3, 7, 10, 8], "hierplane_tree": {"text": "where are you at ? i am in the usa", "root": {"word": "are", "nodeType": "root", "attributes": ["VERB"], "link": "root", "spans": [{"start": 6, "end": 10}], "children": [{"word": "where", "nodeType": "nsubj", "attributes": ["ADV"], "link": "nsubj", "spans": [{"start": 0, "end": 6}]}, {"word": "you", "nodeType": "nsubj", "attributes": ["PRON"], "link": "nsubj", "spans": [{"start": 10, "end": 14}], "children": [{"word": "?", "nodeType": "prep", "attributes": ["PUNCT"], "link": "prep", "spans": [{"start": 17, "end": 19}]}, {"word": "am", "nodeType": "dep", "attributes": ["VERB"], "link": "dep", "spans": [{"start": 21, "end": 24}], "children": [{"word": "i", "nodeType": "dep", "attributes": ["PRON"], "link": "dep", "spans": [{"start": 19, "end": 21}]}, {"word": "in", "nodeType": "prep", "attributes": ["ADP"], "link": "prep", "spans": [{"start": 24, "end": 27}], "children": [{"word": "usa", "nodeType": "pobj", "attributes": ["NOUN"], "link": "pobj", "spans": [{"start": 31, "end": 35}], "children": [{"word": "the", "nodeType": "det", "attributes": ["DET"], "link": "det", "spans": [{"start": 27, "end": 31}]}]}]}]}]}, {"word": "at", "nodeType": "advmod", "attributes": ["ADP"], "link": "advmod", "spans": [{"start": 14, "end": 17}]}]}, "nodeTypeToStyle": {"root": ["color5", "strong"], "dep": ["color5", "strong"], "nsubj": ["color1"], "nsubjpass": ["color1"], "csubj": ["color1"], "csubjpass": ["color1"], "pobj": ["color2"], "dobj": ["color2"], "iobj": ["color2"], "mark": ["color2"], "pcomp": ["color2"], "xcomp": ["color2"], "ccomp": ["color2"], "acomp": ["color2"], "aux": ["color3"], "cop": ["color3"], "det": ["color3"], "conj": ["color3"], "cc": ["color3"], "prep": ["color3"], "number": ["color3"], "possesive": ["color3"], "poss": ["color3"], "discourse": ["color3"], "expletive": ["color3"], "prt": ["color3"], "advcl": ["color3"], "mod": ["color4"], "amod": ["color4"], "tmod": ["color4"], "quantmod": ["color4"], "npadvmod": ["color4"], "infmod": ["color4"], "advmod": ["color4"], "appos": ["color4"], "nn": ["color4"], "neg": ["color0"], "punct": ["color0"]}, "linkToPosition": {"nsubj": "left", "nsubjpass": "left", "csubj": "left", "csubjpass": "left", "pobj": "right", "dobj": "right", "iobj": "right", "pcomp": "right", "xcomp": "right", "ccomp": "right", "acomp": "right"}}}}, {"speaker": 0, "turn": 6, "text": "Florida, watching it rain....", "esvo": [["Florida", "watching"], ["it", "rain"]], "nsvo": [[]], "srl": {"verbs": [{"verb": "watching", "description": "Florida , [V: watching] [ARG1: it rain] ....", "tags": ["O", "O", "B-V", "B-ARG1", "I-ARG1", "O"]}, {"verb": "rain", "description": "Florida , watching it [V: rain] ....", "tags": ["O", "O", "O", "O", "B-V", "O"]}], "words": ["Florida", ",", "watching", "it", "rain", "...."]}, "deps": {"arc_loss": 0.6021239757537842, "tag_loss": 0.30414214730262756, "loss": 0.9062660932540894, "words": ["Florida", ",", "watching", "it", "rain", "...."], "pos": ["PROPN", "PUNCT", "VERB", "PRON", "VERB", "PUNCT"], "predicted_dependencies": ["root", "dep", "dep", "advmod", "dep", "dep"], "predicted_heads": [0, 1, 2, 3, 3, 5], "hierplane_tree": {"text": "Florida , watching it rain ....", "root": {"word": "Florida", "nodeType": "root", "attributes": ["PROPN"], "link": "root", "spans": [{"start": 0, "end": 8}], "children": [{"word": ",", "nodeType": "dep", "attributes": ["PUNCT"], "link": "dep", "spans": [{"start": 8, "end": 10}], "children": [{"word": "watching", "nodeType": "dep", "attributes": ["VERB"], "link": "dep", "spans": [{"start": 10, "end": 19}], "children": [{"word": "it", "nodeType": "advmod", "attributes": ["PRON"], "link": "advmod", "spans": [{"start": 19, "end": 22}]}, {"word": "rain", "nodeType": "dep", "attributes": ["VERB"], "link": "dep", "spans": [{"start": 22, "end": 27}], "children": [{"word": "....", "nodeType": "dep", "attributes": ["PUNCT"], "link": "dep", "spans": [{"start": 27, "end": 32}]}]}]}]}]}, "nodeTypeToStyle": {"root": ["color5", "strong"], "dep": ["color5", "strong"], "nsubj": ["color1"], "nsubjpass": ["color1"], "csubj": ["color1"], "csubjpass": ["color1"], "pobj": ["color2"], "dobj": ["color2"], "iobj": ["color2"], "mark": ["color2"], "pcomp": ["color2"], "xcomp": ["color2"], "ccomp": ["color2"], "acomp": ["color2"], "aux": ["color3"], "cop": ["color3"], "det": ["color3"], "conj": ["color3"], "cc": ["color3"], "prep": ["color3"], "number": ["color3"], "possesive": ["color3"], "poss": ["color3"], "discourse": ["color3"], "expletive": ["color3"], "prt": ["color3"], "advcl": ["color3"], "mod": ["color4"], "amod": ["color4"], "tmod": ["color4"], "quantmod": ["color4"], "npadvmod": ["color4"], "infmod": ["color4"], "advmod": ["color4"], "appos": ["color4"], "nn": ["color4"], "neg": ["color0"], "punct": ["color0"]}, "linkToPosition": {"nsubj": "left", "nsubjpass": "left", "csubj": "left", "csubjpass": "left", "pobj": "right", "dobj": "right", "iobj": "right", "pcomp": "right", "xcomp": "right", "ccomp": "right", "acomp": "right"}}}}, {"speaker": 1, "turn": 6, "text": "yeah. i am on the mississipi in iowa and we got trees down everywhere", "esvo": [["we", "got", "trees"]], "nsvo": [[], [{"subject": ["we"], "predicate": ["got"], "object": ["trees"]}, {"subject": ["we"], "predicate": ["got"], "object": ["trees"]}]], "srl": {"verbs": [{"verb": "am", "description": "[ARGM-DIS: yeah] . [ARG1: i] [V: am] [ARG2: on the mississipi in iowa] and we got trees down everywhere", "tags": ["B-ARGM-DIS", "O", "B-ARG1", "B-V", "B-ARG2", "I-ARG2", "I-ARG2", "I-ARG2", "I-ARG2", "O", "O", "O", "O", "O", "O"]}, {"verb": "got", "description": "yeah . i am on the mississipi in iowa and [ARG0: we] [V: got] [ARG1: trees] [ARGM-LOC: down] [ARGM-LOC: everywhere]", "tags": ["O", "O", "O", "O", "O", "O", "O", "O", "O", "O", "B-ARG0", "B-V", "B-ARG1", "B-ARGM-LOC", "B-ARGM-LOC"]}], "words": ["yeah", ".", "i", "am", "on", "the", "mississipi", "in", "iowa", "and", "we", "got", "trees", "down", "everywhere"]}, "deps": {"arc_loss": 0.33316996693611145, "tag_loss": 0.17154757678508759, "loss": 0.5047175288200378, "words": ["yeah", ".", "i", "am", "on", "the", "mississipi", "in", "iowa", "and", "we", "got", "trees", "down", "everywhere"], "pos": ["INTJ", "PUNCT", "PRON", "VERB", "ADP", "DET", "NOUN", "ADP", "NOUN", "CCONJ", "PRON", "VERB", "NOUN", "ADV", "ADV"], "predicted_dependencies": ["root", "nsubj", "dep", "dep", "prep", "det", "pobj", "prep", "pobj", "dep", "nsubj", "dep", "dep", "advmod", "advmod"], "predicted_heads": [0, 1, 1, 1, 4, 7, 5, 4, 8, 4, 12, 4, 4, 13, 13], "hierplane_tree": {"text": "yeah . i am on the mississipi in iowa and we got trees down everywhere", "root": {"word": "yeah", "nodeType": "root", "attributes": ["INTJ"], "link": "root", "spans": [{"start": 0, "end": 5}], "children": [{"word": ".", "nodeType": "nsubj", "attributes": ["PUNCT"], "link": "nsubj", "spans": [{"start": 5, "end": 7}]}, {"word": "i", "nodeType": "dep", "attributes": ["PRON"], "link": "dep", "spans": [{"start": 7, "end": 9}]}, {"word": "am", "nodeType": "dep", "attributes": ["VERB"], "link": "dep", "spans": [{"start": 9, "end": 12}], "children": [{"word": "on", "nodeType": "prep", "attributes": ["ADP"], "link": "prep", "spans": [{"start": 12, "end": 15}], "children": [{"word": "mississipi", "nodeType": "pobj", "attributes": ["NOUN"], "link": "pobj", "spans": [{"start": 19, "end": 30}], "children": [{"word": "the", "nodeType": "det", "attributes": ["DET"], "link": "det", "spans": [{"start": 15, "end": 19}]}]}]}, {"word": "in", "nodeType": "prep", "attributes": ["ADP"], "link": "prep", "spans": [{"start": 30, "end": 33}], "children": [{"word": "iowa", "nodeType": "pobj", "attributes": ["NOUN"], "link": "pobj", "spans": [{"start": 33, "end": 38}]}]}, {"word": "and", "nodeType": "dep", "attributes": ["CCONJ"], "link": "dep", "spans": [{"start": 38, "end": 42}]}, {"word": "got", "nodeType": "dep", "attributes": ["VERB"], "link": "dep", "spans": [{"start": 45, "end": 49}], "children": [{"word": "we", "nodeType": "nsubj", "attributes": ["PRON"], "link": "nsubj", "spans": [{"start": 42, "end": 45}]}]}, {"word": "trees", "nodeType": "dep", "attributes": ["NOUN"], "link": "dep", "spans": [{"start": 49, "end": 55}], "children": [{"word": "down", "nodeType": "advmod", "attributes": ["ADV"], "link": "advmod", "spans": [{"start": 55, "end": 60}]}, {"word": "everywhere", "nodeType": "advmod", "attributes": ["ADV"], "link": "advmod", "spans": [{"start": 60, "end": 71}]}]}]}]}, "nodeTypeToStyle": {"root": ["color5", "strong"], "dep": ["color5", "strong"], "nsubj": ["color1"], "nsubjpass": ["color1"], "csubj": ["color1"], "csubjpass": ["color1"], "pobj": ["color2"], "dobj": ["color2"], "iobj": ["color2"], "mark": ["color2"], "pcomp": ["color2"], "xcomp": ["color2"], "ccomp": ["color2"], "acomp": ["color2"], "aux": ["color3"], "cop": ["color3"], "det": ["color3"], "conj": ["color3"], "cc": ["color3"], "prep": ["color3"], "number": ["color3"], "possesive": ["color3"], "poss": ["color3"], "discourse": ["color3"], "expletive": ["color3"], "prt": ["color3"], "advcl": ["color3"], "mod": ["color4"], "amod": ["color4"], "tmod": ["color4"], "quantmod": ["color4"], "npadvmod": ["color4"], "infmod": ["color4"], "advmod": ["color4"], "appos": ["color4"], "nn": ["color4"], "neg": ["color0"], "punct": ["color0"]}, "linkToPosition": {"nsubj": "left", "nsubjpass": "left", "csubj": "left", "csubjpass": "left", "pobj": "right", "dobj": "right", "iobj": "right", "pcomp": "right", "xcomp": "right", "ccomp": "right", "acomp": "right"}}}}, {"speaker": 0, "turn": 7, "text": "We have more rain coming!  It sucks", "esvo": [["We", "have"], ["more rain", "coming"], ["It", "sucks"]], "nsvo": [[{"subject": ["We"], "predicate": ["coming"], "object": ["rain"]}], []], "srl": {"verbs": [{"verb": "have", "description": "[ARG0: We] [V: have] [ARG1: more rain coming] ! It sucks", "tags": ["B-ARG0", "B-V", "B-ARG1", "I-ARG1", "I-ARG1", "O", "O", "O"]}, {"verb": "coming", "description": "We have [ARG1: more rain] [V: coming] ! It sucks", "tags": ["O", "O", "B-ARG1", "I-ARG1", "B-V", "O", "O", "O"]}, {"verb": "sucks", "description": "We have more rain coming ! [ARG0: It] [V: sucks]", "tags": ["O", "O", "O", "O", "O", "O", "B-ARG0", "B-V"]}], "words": ["We", "have", "more", "rain", "coming", "!", "It", "sucks"]}, "deps": {"arc_loss": 0.7074912190437317, "tag_loss": 0.32294416427612305, "loss": 1.03043532371521, "words": ["We", "have", "more", "rain", "coming", "!", "It", "sucks"], "pos": ["PRON", "VERB", "ADJ", "NOUN", "VERB", "PUNCT", "PRON", "VERB"], "predicted_dependencies": ["nsubj", "dep", "dep", "root", "dep", "dep", "amod", "dep"], "predicted_heads": [4, 5, 4, 0, 4, 5, 8, 5], "hierplane_tree": {"text": "We have more rain coming ! It sucks", "root": {"word": "rain", "nodeType": "root", "attributes": ["NOUN"], "link": "root", "spans": [{"start": 13, "end": 18}], "children": [{"word": "We", "nodeType": "nsubj", "attributes": ["PRON"], "link": "nsubj", "spans": [{"start": 0, "end": 3}]}, {"word": "more", "nodeType": "dep", "attributes": ["ADJ"], "link": "dep", "spans": [{"start": 8, "end": 13}]}, {"word": "coming", "nodeType": "dep", "attributes": ["VERB"], "link": "dep", "spans": [{"start": 18, "end": 25}], "children": [{"word": "have", "nodeType": "dep", "attributes": ["VERB"], "link": "dep", "spans": [{"start": 3, "end": 8}]}, {"word": "!", "nodeType": "dep", "attributes": ["PUNCT"], "link": "dep", "spans": [{"start": 25, "end": 27}]}, {"word": "sucks", "nodeType": "dep", "attributes": ["VERB"], "link": "dep", "spans": [{"start": 30, "end": 36}], "children": [{"word": "It", "nodeType": "amod", "attributes": ["PRON"], "link": "amod", "spans": [{"start": 27, "end": 30}]}]}]}]}, "nodeTypeToStyle": {"root": ["color5", "strong"], "dep": ["color5", "strong"], "nsubj": ["color1"], "nsubjpass": ["color1"], "csubj": ["color1"], "csubjpass": ["color1"], "pobj": ["color2"], "dobj": ["color2"], "iobj": ["color2"], "mark": ["color2"], "pcomp": ["color2"], "xcomp": ["color2"], "ccomp": ["color2"], "acomp": ["color2"], "aux": ["color3"], "cop": ["color3"], "det": ["color3"], "conj": ["color3"], "cc": ["color3"], "prep": ["color3"], "number": ["color3"], "possesive": ["color3"], "poss": ["color3"], "discourse": ["color3"], "expletive": ["color3"], "prt": ["color3"], "advcl": ["color3"], "mod": ["color4"], "amod": ["color4"], "tmod": ["color4"], "quantmod": ["color4"], "npadvmod": ["color4"], "infmod": ["color4"], "advmod": ["color4"], "appos": ["color4"], "nn": ["color4"], "neg": ["color0"], "punct": ["color0"]}, "linkToPosition": {"nsubj": "left", "nsubjpass": "left", "csubj": "left", "csubjpass": "left", "pobj": "right", "dobj": "right", "iobj": "right", "pcomp": "right", "xcomp": "right", "ccomp": "right", "acomp": "right"}}}}, {"speaker": 1, "turn": 7, "text": "idk what they want us to do but this aint it. weirdest hit ever!", "esvo": [["they", "want"], ["us", "do"], ["weirdest", "hit"]], "nsvo": [[], []], "srl": {"verbs": [{"verb": "idk", "description": "[V: idk] [ARG1: what they want us to do] but this ai nt it . weirdest hit ever !", "tags": ["B-V", "B-ARG1", "I-ARG1", "I-ARG1", "I-ARG1", "I-ARG1", "I-ARG1", "O", "O", "O", "O", "O", "O", "O", "O", "O", "O"]}, {"verb": "want", "description": "idk what [ARG0: they] [V: want] [ARG1: us to do] but this ai nt it . weirdest hit ever !", "tags": ["O", "O", "B-ARG0", "B-V", "B-ARG1", "I-ARG1", "I-ARG1", "O", "O", "O", "O", "O", "O", "O", "O", "O", "O"]}, {"verb": "do", "description": "idk [ARG1: what] they want [ARG0: us] to [V: do] but this ai nt it . weirdest hit ever !", "tags": ["O", "B-ARG1", "O", "O", "B-ARG0", "O", "B-V", "O", "O", "O", "O", "O", "O", "O", "O", "O", "O"]}, {"verb": "ai", "description": "idk what they want us to do but [ARG1: this] [V: ai] nt [ARG2: it] . weirdest hit ever !", "tags": ["O", "O", "O", "O", "O", "O", "O", "O", "B-ARG1", "B-V", "O", "B-ARG2", "O", "O", "O", "O", "O"]}, {"verb": "hit", "description": "idk what they want us to do but this ai nt it . [ARGM-ADJ: weirdest] [V: hit] [ARGM-TMP: ever] !", "tags": ["O", "O", "O", "O", "O", "O", "O", "O", "O", "O", "O", "O", "O", "B-ARGM-ADJ", "B-V", "B-ARGM-TMP", "O"]}], "words": ["idk", "what", "they", "want", "us", "to", "do", "but", "this", "ai", "nt", "it", ".", "weirdest", "hit", "ever", "!"]}, "deps": {"arc_loss": 0.8933823704719543, "tag_loss": 0.39011460542678833, "loss": 1.2834969758987427, "words": ["idk", "what", "they", "want", "us", "to", "do", "but", "this", "ai", "nt", "it", ".", "weirdest", "hit", "ever", "!"], "pos": ["VERB", "PRON", "PRON", "VERB", "PRON", "PART", "VERB", "CCONJ", "DET", "VERB", "PART", "PRON", "PUNCT", "ADJ", "VERB", "ADV", "PUNCT"], "predicted_dependencies": ["root", "nsubj", "nsubj", "dep", "dep", "dep", "dep", "advmod", "dep", "dep", "dep", "dep", "dep", "dep", "dep", "dep", "dep"], "predicted_heads": [0, 4, 4, 1, 4, 5, 6, 1, 10, 8, 10, 15, 15, 15, 10, 15, 16], "hierplane_tree": {"text": "idk what they want us to do but this ai nt it . weirdest hit ever !", "root": {"word": "idk", "nodeType": "root", "attributes": ["VERB"], "link": "root", "spans": [{"start": 0, "end": 4}], "children": [{"word": "want", "nodeType": "dep", "attributes": ["VERB"], "link": "dep", "spans": [{"start": 14, "end": 19}], "children": [{"word": "what", "nodeType": "nsubj", "attributes": ["PRON"], "link": "nsubj", "spans": [{"start": 4, "end": 9}]}, {"word": "they", "nodeType": "nsubj", "attributes": ["PRON"], "link": "nsubj", "spans": [{"start": 9, "end": 14}]}, {"word": "us", "nodeType": "dep", "attributes": ["PRON"], "link": "dep", "spans": [{"start": 19, "end": 22}], "children": [{"word": "to", "nodeType": "dep", "attributes": ["PART"], "link": "dep", "spans": [{"start": 22, "end": 25}], "children": [{"word": "do", "nodeType": "dep", "attributes": ["VERB"], "link": "dep", "spans": [{"start": 25, "end": 28}]}]}]}]}, {"word": "but", "nodeType": "advmod", "attributes": ["CCONJ"], "link": "advmod", "spans": [{"start": 28, "end": 32}], "children": [{"word": "ai", "nodeType": "dep", "attributes": ["VERB"], "link": "dep", "spans": [{"start": 37, "end": 40}], "children": [{"word": "this", "nodeType": "dep", "attributes": ["DET"], "link": "dep", "spans": [{"start": 32, "end": 37}]}, {"word": "nt", "nodeType": "dep", "attributes": ["PART"], "link": "dep", "spans": [{"start": 40, "end": 43}]}, {"word": "hit", "nodeType": "dep", "attributes": ["VERB"], "link": "dep", "spans": [{"start": 57, "end": 61}], "children": [{"word": "it", "nodeType": "dep", "attributes": ["PRON"], "link": "dep", "spans": [{"start": 43, "end": 46}]}, {"word": ".", "nodeType": "dep", "attributes": ["PUNCT"], "link": "dep", "spans": [{"start": 46, "end": 48}]}, {"word": "weirdest", "nodeType": "dep", "attributes": ["ADJ"], "link": "dep", "spans": [{"start": 48, "end": 57}]}, {"word": "ever", "nodeType": "dep", "attributes": ["ADV"], "link": "dep", "spans": [{"start": 61, "end": 66}], "children": [{"word": "!", "nodeType": "dep", "attributes": ["PUNCT"], "link": "dep", "spans": [{"start": 66, "end": 68}]}]}]}]}]}]}, "nodeTypeToStyle": {"root": ["color5", "strong"], "dep": ["color5", "strong"], "nsubj": ["color1"], "nsubjpass": ["color1"], "csubj": ["color1"], "csubjpass": ["color1"], "pobj": ["color2"], "dobj": ["color2"], "iobj": ["color2"], "mark": ["color2"], "pcomp": ["color2"], "xcomp": ["color2"], "ccomp": ["color2"], "acomp": ["color2"], "aux": ["color3"], "cop": ["color3"], "det": ["color3"], "conj": ["color3"], "cc": ["color3"], "prep": ["color3"], "number": ["color3"], "possesive": ["color3"], "poss": ["color3"], "discourse": ["color3"], "expletive": ["color3"], "prt": ["color3"], "advcl": ["color3"], "mod": ["color4"], "amod": ["color4"], "tmod": ["color4"], "quantmod": ["color4"], "npadvmod": ["color4"], "infmod": ["color4"], "advmod": ["color4"], "appos": ["color4"], "nn": ["color4"], "neg": ["color0"], "punct": ["color0"]}, "linkToPosition": {"nsubj": "left", "nsubjpass": "left", "csubj": "left", "csubjpass": "left", "pobj": "right", "dobj": "right", "iobj": "right", "pcomp": "right", "xcomp": "right", "ccomp": "right", "acomp": "right"}}}}, {"speaker": 0, "turn": 8, "text": "It is!  But today has been so slow", "esvo": [["today", "been"]], "nsvo": [[], [{"subject": ["today"], "predicate": ["been"], "object": ["slow"]}]], "srl": {"verbs": [{"verb": "is", "description": "[ARG1: It] [V: is] ! But today has been so slow", "tags": ["B-ARG1", "B-V", "O", "O", "O", "O", "O", "O", "O"]}, {"verb": "has", "description": "It is ! But today [V: has] been so slow", "tags": ["O", "O", "O", "O", "O", "B-V", "O", "O", "O"]}, {"verb": "been", "description": "It is ! But [ARG1: today] has [V: been] [ARG2: so slow]", "tags": ["O", "O", "O", "O", "B-ARG1", "O", "B-V", "B-ARG2", "I-ARG2"]}], "words": ["It", "is", "!", "But", "today", "has", "been", "so", "slow"]}, "deps": {"arc_loss": 1.8011000156402588, "tag_loss": 0.2553807199001312, "loss": 2.056480646133423, "words": ["It", "is", "!", "But", "today", "has", "been", "so", "slow"], "pos": ["PRON", "VERB", "PUNCT", "CCONJ", "NOUN", "VERB", "VERB", "ADV", "ADJ"], "predicted_dependencies": ["nsubj", "cop", "dep", "nsubj", "dep", "aux", "cop", "advmod", "root"], "predicted_heads": [2, 4, 2, 9, 4, 9, 9, 9, 0], "hierplane_tree": {"text": "It is ! But today has been so slow", "root": {"word": "slow", "nodeType": "root", "attributes": ["ADJ"], "link": "root", "spans": [{"start": 30, "end": 35}], "children": [{"word": "But", "nodeType": "nsubj", "attributes": ["CCONJ"], "link": "nsubj", "spans": [{"start": 8, "end": 12}], "children": [{"word": "is", "nodeType": "cop", "attributes": ["VERB"], "link": "cop", "spans": [{"start": 3, "end": 6}], "children": [{"word": "It", "nodeType": "nsubj", "attributes": ["PRON"], "link": "nsubj", "spans": [{"start": 0, "end": 3}]}, {"word": "!", "nodeType": "dep", "attributes": ["PUNCT"], "link": "dep", "spans": [{"start": 6, "end": 8}]}]}, {"word": "today", "nodeType": "dep", "attributes": ["NOUN"], "link": "dep", "spans": [{"start": 12, "end": 18}]}]}, {"word": "has", "nodeType": "aux", "attributes": ["VERB"], "link": "aux", "spans": [{"start": 18, "end": 22}]}, {"word": "been", "nodeType": "cop", "attributes": ["VERB"], "link": "cop", "spans": [{"start": 22, "end": 27}]}, {"word": "so", "nodeType": "advmod", "attributes": ["ADV"], "link": "advmod", "spans": [{"start": 27, "end": 30}]}]}, "nodeTypeToStyle": {"root": ["color5", "strong"], "dep": ["color5", "strong"], "nsubj": ["color1"], "nsubjpass": ["color1"], "csubj": ["color1"], "csubjpass": ["color1"], "pobj": ["color2"], "dobj": ["color2"], "iobj": ["color2"], "mark": ["color2"], "pcomp": ["color2"], "xcomp": ["color2"], "ccomp": ["color2"], "acomp": ["color2"], "aux": ["color3"], "cop": ["color3"], "det": ["color3"], "conj": ["color3"], "cc": ["color3"], "prep": ["color3"], "number": ["color3"], "possesive": ["color3"], "poss": ["color3"], "discourse": ["color3"], "expletive": ["color3"], "prt": ["color3"], "advcl": ["color3"], "mod": ["color4"], "amod": ["color4"], "tmod": ["color4"], "quantmod": ["color4"], "npadvmod": ["color4"], "infmod": ["color4"], "advmod": ["color4"], "appos": ["color4"], "nn": ["color4"], "neg": ["color0"], "punct": ["color0"]}, "linkToPosition": {"nsubj": "left", "nsubjpass": "left", "csubj": "left", "csubjpass": "left", "pobj": "right", "dobj": "right", "iobj": "right", "pcomp": "right", "xcomp": "right", "ccomp": "right", "acomp": "right"}}}}, {"speaker": 1, "turn": 8, "text": "no one has posted all weekend and now its a holiday.", "esvo": [["one", "posted"]], "nsvo": [[]], "srl": {"verbs": [{"verb": "has", "description": "no one [V: has] posted all weekend and now its a holiday .", "tags": ["O", "O", "B-V", "O", "O", "O", "O", "O", "O", "O", "O", "O"]}, {"verb": "posted", "description": "[ARG0: no one] has [V: posted] [ARGM-TMP: all weekend] and now its a holiday .", "tags": ["B-ARG0", "I-ARG0", "O", "B-V", "B-ARGM-TMP", "I-ARGM-TMP", "O", "O", "O", "O", "O", "O"]}], "words": ["no", "one", "has", "posted", "all", "weekend", "and", "now", "its", "a", "holiday", "."]}, "deps": {"arc_loss": 1.3882088661193848, "tag_loss": 0.38953039050102234, "loss": 1.7777392864227295, "words": ["no", "one", "has", "posted", "all", "weekend", "and", "now", "its", "a", "holiday", "."], "pos": ["DET", "NOUN", "VERB", "VERB", "DET", "NOUN", "CCONJ", "ADV", "PRON", "DET", "NOUN", "PUNCT"], "predicted_dependencies": ["amod", "nsubj", "aux", "root", "dep", "tmod", "cc", "dep", "dep", "det", "dep", "amod"], "predicted_heads": [2, 4, 4, 0, 6, 4, 6, 11, 11, 11, 6, 11], "hierplane_tree": {"text": "no one has posted all weekend and now its a holiday .", "root": {"word": "posted", "nodeType": "root", "attributes": ["VERB"], "link": "root", "spans": [{"start": 11, "end": 18}], "children": [{"word": "one", "nodeType": "nsubj", "attributes": ["NOUN"], "link": "nsubj", "spans": [{"start": 3, "end": 7}], "children": [{"word": "no", "nodeType": "amod", "attributes": ["DET"], "link": "amod", "spans": [{"start": 0, "end": 3}]}]}, {"word": "has", "nodeType": "aux", "attributes": ["VERB"], "link": "aux", "spans": [{"start": 7, "end": 11}]}, {"word": "weekend", "nodeType": "tmod", "attributes": ["NOUN"], "link": "tmod", "spans": [{"start": 22, "end": 30}], "children": [{"word": "all", "nodeType": "dep", "attributes": ["DET"], "link": "dep", "spans": [{"start": 18, "end": 22}]}, {"word": "and", "nodeType": "cc", "attributes": ["CCONJ"], "link": "cc", "spans": [{"start": 30, "end": 34}]}, {"word": "holiday", "nodeType": "dep", "attributes": ["NOUN"], "link": "dep", "spans": [{"start": 44, "end": 52}], "children": [{"word": "now", "nodeType": "dep", "attributes": ["ADV"], "link": "dep", "spans": [{"start": 34, "end": 38}]}, {"word": "its", "nodeType": "dep", "attributes": ["PRON"], "link": "dep", "spans": [{"start": 38, "end": 42}]}, {"word": "a", "nodeType": "det", "attributes": ["DET"], "link": "det", "spans": [{"start": 42, "end": 44}]}, {"word": ".", "nodeType": "amod", "attributes": ["PUNCT"], "link": "amod", "spans": [{"start": 52, "end": 54}]}]}]}]}, "nodeTypeToStyle": {"root": ["color5", "strong"], "dep": ["color5", "strong"], "nsubj": ["color1"], "nsubjpass": ["color1"], "csubj": ["color1"], "csubjpass": ["color1"], "pobj": ["color2"], "dobj": ["color2"], "iobj": ["color2"], "mark": ["color2"], "pcomp": ["color2"], "xcomp": ["color2"], "ccomp": ["color2"], "acomp": ["color2"], "aux": ["color3"], "cop": ["color3"], "det": ["color3"], "conj": ["color3"], "cc": ["color3"], "prep": ["color3"], "number": ["color3"], "possesive": ["color3"], "poss": ["color3"], "discourse": ["color3"], "expletive": ["color3"], "prt": ["color3"], "advcl": ["color3"], "mod": ["color4"], "amod": ["color4"], "tmod": ["color4"], "quantmod": ["color4"], "npadvmod": ["color4"], "infmod": ["color4"], "advmod": ["color4"], "appos": ["color4"], "nn": ["color4"], "neg": ["color0"], "punct": ["color0"]}, "linkToPosition": {"nsubj": "left", "nsubjpass": "left", "csubj": "left", "csubjpass": "left", "pobj": "right", "dobj": "right", "iobj": "right", "pcomp": "right", "xcomp": "right", "ccomp": "right", "acomp": "right"}}}}, {"speaker": 0, "turn": 9, "text": "I am hoping it picks up soon", "esvo": [["I", "hoping"], ["it", "picks"]], "nsvo": [[]], "srl": {"verbs": [{"verb": "am", "description": "I [V: am] hoping it picks up soon", "tags": ["O", "B-V", "O", "O", "O", "O", "O"]}, {"verb": "hoping", "description": "[ARG0: I] am [V: hoping] [ARG1: it picks up soon]", "tags": ["B-ARG0", "O", "B-V", "B-ARG1", "I-ARG1", "I-ARG1", "I-ARG1"]}, {"verb": "picks", "description": "I am hoping [ARG1: it] [V: picks] up [ARGM-TMP: soon]", "tags": ["O", "O", "O", "B-ARG1", "B-V", "O", "B-ARGM-TMP"]}], "words": ["I", "am", "hoping", "it", "picks", "up", "soon"]}, "deps": {"arc_loss": 0.638809859752655, "tag_loss": 0.1653279811143875, "loss": 0.8041378259658813, "words": ["I", "am", "hoping", "it", "picks", "up", "soon"], "pos": ["PRON", "VERB", "VERB", "PRON", "VERB", "ADP", "ADV"], "predicted_dependencies": ["nsubj", "cop", "root", "nsubj", "ccomp", "advmod", "advmod"], "predicted_heads": [3, 3, 0, 5, 3, 5, 5], "hierplane_tree": {"text": "I am hoping it picks up soon", "root": {"word": "hoping", "nodeType": "root", "attributes": ["VERB"], "link": "root", "spans": [{"start": 5, "end": 12}], "children": [{"word": "I", "nodeType": "nsubj", "attributes": ["PRON"], "link": "nsubj", "spans": [{"start": 0, "end": 2}]}, {"word": "am", "nodeType": "cop", "attributes": ["VERB"], "link": "cop", "spans": [{"start": 2, "end": 5}]}, {"word": "picks", "nodeType": "ccomp", "attributes": ["VERB"], "link": "ccomp", "spans": [{"start": 15, "end": 21}], "children": [{"word": "it", "nodeType": "nsubj", "attributes": ["PRON"], "link": "nsubj", "spans": [{"start": 12, "end": 15}]}, {"word": "up", "nodeType": "advmod", "attributes": ["ADP"], "link": "advmod", "spans": [{"start": 21, "end": 24}]}, {"word": "soon", "nodeType": "advmod", "attributes": ["ADV"], "link": "advmod", "spans": [{"start": 24, "end": 29}]}]}]}, "nodeTypeToStyle": {"root": ["color5", "strong"], "dep": ["color5", "strong"], "nsubj": ["color1"], "nsubjpass": ["color1"], "csubj": ["color1"], "csubjpass": ["color1"], "pobj": ["color2"], "dobj": ["color2"], "iobj": ["color2"], "mark": ["color2"], "pcomp": ["color2"], "xcomp": ["color2"], "ccomp": ["color2"], "acomp": ["color2"], "aux": ["color3"], "cop": ["color3"], "det": ["color3"], "conj": ["color3"], "cc": ["color3"], "prep": ["color3"], "number": ["color3"], "possesive": ["color3"], "poss": ["color3"], "discourse": ["color3"], "expletive": ["color3"], "prt": ["color3"], "advcl": ["color3"], "mod": ["color4"], "amod": ["color4"], "tmod": ["color4"], "quantmod": ["color4"], "npadvmod": ["color4"], "infmod": ["color4"], "advmod": ["color4"], "appos": ["color4"], "nn": ["color4"], "neg": ["color0"], "punct": ["color0"]}, "linkToPosition": {"nsubj": "left", "nsubjpass": "left", "csubj": "left", "csubjpass": "left", "pobj": "right", "dobj": "right", "iobj": "right", "pcomp": "right", "xcomp": "right", "ccomp": "right", "acomp": "right"}}}}, {"speaker": 1, "turn": 9, "text": "ok this is ten turns! it better let us out!", "esvo": [["it", "let", "us"]], "nsvo": [[], [{"subject": ["it"], "predicate": ["let"], "object": ["us"]}]], "srl": {"verbs": [{"verb": "is", "description": "[ARGM-DIS: ok] [ARG1: this] [V: is] [ARG2: ten turns] ! it better let us out !", "tags": ["B-ARGM-DIS", "B-ARG1", "B-V", "B-ARG2", "I-ARG2", "O", "O", "O", "O", "O", "O", "O"]}, {"verb": "let", "description": "ok this is ten turns ! [ARG0: it] [ARGM-ADV: better] [V: let] [ARG1: us] [ARGM-DIR: out] !", "tags": ["O", "O", "O", "O", "O", "O", "B-ARG0", "B-ARGM-ADV", "B-V", "B-ARG1", "B-ARGM-DIR", "O"]}], "words": ["ok", "this", "is", "ten", "turns", "!", "it", "better", "let", "us", "out", "!"]}, "deps": {"arc_loss": 0.875593364238739, "tag_loss": 0.46387410163879395, "loss": 1.3394675254821777, "words": ["ok", "this", "is", "ten", "turns", "!", "it", "better", "let", "us", "out", "!"], "pos": ["INTJ", "DET", "VERB", "NUM", "NOUN", "PUNCT", "PRON", "ADV", "VERB", "PRON", "ADP", "PUNCT"], "predicted_dependencies": ["advmod", "nsubj", "cop", "root", "advmod", "dep", "advmod", "dep", "dep", "dep", "dep", "dep"], "predicted_heads": [3, 3, 4, 0, 4, 5, 8, 6, 8, 9, 10, 10], "hierplane_tree": {"text": "ok this is ten turns ! it better let us out !", "root": {"word": "ten", "nodeType": "root", "attributes": ["NUM"], "link": "root", "spans": [{"start": 11, "end": 15}], "children": [{"word": "is", "nodeType": "cop", "attributes": ["VERB"], "link": "cop", "spans": [{"start": 8, "end": 11}], "children": [{"word": "ok", "nodeType": "advmod", "attributes": ["INTJ"], "link": "advmod", "spans": [{"start": 0, "end": 3}]}, {"word": "this", "nodeType": "nsubj", "attributes": ["DET"], "link": "nsubj", "spans": [{"start": 3, "end": 8}]}]}, {"word": "turns", "nodeType": "advmod", "attributes": ["NOUN"], "link": "advmod", "spans": [{"start": 15, "end": 21}], "children": [{"word": "!", "nodeType": "dep", "attributes": ["PUNCT"], "link": "dep", "spans": [{"start": 21, "end": 23}], "children": [{"word": "better", "nodeType": "dep", "attributes": ["ADV"], "link": "dep", "spans": [{"start": 26, "end": 33}], "children": [{"word": "it", "nodeType": "advmod", "attributes": ["PRON"], "link": "advmod", "spans": [{"start": 23, "end": 26}]}, {"word": "let", "nodeType": "dep", "attributes": ["VERB"], "link": "dep", "spans": [{"start": 33, "end": 37}], "children": [{"word": "us", "nodeType": "dep", "attributes": ["PRON"], "link": "dep", "spans": [{"start": 37, "end": 40}], "children": [{"word": "out", "nodeType": "dep", "attributes": ["ADP"], "link": "dep", "spans": [{"start": 40, "end": 44}]}, {"word": "!", "nodeType": "dep", "attributes": ["PUNCT"], "link": "dep", "spans": [{"start": 44, "end": 46}]}]}]}]}]}]}]}, "nodeTypeToStyle": {"root": ["color5", "strong"], "dep": ["color5", "strong"], "nsubj": ["color1"], "nsubjpass": ["color1"], "csubj": ["color1"], "csubjpass": ["color1"], "pobj": ["color2"], "dobj": ["color2"], "iobj": ["color2"], "mark": ["color2"], "pcomp": ["color2"], "xcomp": ["color2"], "ccomp": ["color2"], "acomp": ["color2"], "aux": ["color3"], "cop": ["color3"], "det": ["color3"], "conj": ["color3"], "cc": ["color3"], "prep": ["color3"], "number": ["color3"], "possesive": ["color3"], "poss": ["color3"], "discourse": ["color3"], "expletive": ["color3"], "prt": ["color3"], "advcl": ["color3"], "mod": ["color4"], "amod": ["color4"], "tmod": ["color4"], "quantmod": ["color4"], "npadvmod": ["color4"], "infmod": ["color4"], "advmod": ["color4"], "appos": ["color4"], "nn": ["color4"], "neg": ["color0"], "punct": ["color0"]}, "linkToPosition": {"nsubj": "left", "nsubjpass": "left", "csubj": "left", "csubjpass": "left", "pobj": "right", "dobj": "right", "iobj": "right", "pcomp": "right", "xcomp": "right", "ccomp": "right", "acomp": "right"}}}}]}